README.md
setup.py
libsparse/__init__.py
libsparse/libsparse.py
libsparse.egg-info/PKG-INFO
libsparse.egg-info/SOURCES.txt
libsparse.egg-info/dependency_links.txt
libsparse.egg-info/top_level.txt